Topsis_Ishav_101903773
