Metadata-Version: 2.1
Name: Topsis-Ishav-101903773
Version: 1.0.0
Summary: A Python package implementing TOPSIS technique by Ishav_101903773.
Home-page: UNKNOWN
Author: Ishav Gupta
Author-email: igupta1_be19@thapar.edu
License: MIT
Keywords: topsis,topsis implementation
Platform: UNKNOWN
Classifier: Development Status :: 3 - Alpha
Classifier: Intended Audience :: Developers
Classifier: Topic :: Software Development :: Build Tools
Classifier: License :: OSI Approved :: MIT License
Classifier: Programming Language :: Python :: 3
Classifier: Programming Language :: Python :: 3.4
Classifier: Programming Language :: Python :: 3.5
Classifier: Programming Language :: Python :: 3.6
Classifier: Programming Language :: Python :: 3.7
Classifier: Programming Language :: Python :: 3.8
Classifier: Programming Language :: Python :: 3.9
